{
  "updatedAt": "2026-07-07T16:13:39",
  "indices": [
    {
      "name": "KOSPI",
      "value": 7656.31,
      "change": -4.91
    },
    {
      "name": "KOSDAQ",
      "value": 831.23,
      "change": -1.87
    },
    {
      "name": "S&P 500",
      "value": 7508.4,
      "change": -0.39
    },
    {
      "name": "NASDAQ",
      "value": 25877.23,
      "change": -0.93
    }
  ],
  "fx": {
    "name": "USD/KRW",
    "value": 1514.05,
    "change": -1.11
  },
  "stocks": [
    {
      "group": "fixed",
      "name": "삼성전자",
      "code": "005930",
      "logo": "삼전",
      "price": 296000.0,
      "change": -6.92,
      "prevClose": 318000.0,
      "trend": [
        1.0912,
        1.1284,
        1.0625,
        0.9662,
        1.0456,
        1.0743,
        1.0
      ],
      "volume": 31975948,
      "reasons": []
    },
    {
      "group": "fixed",
      "name": "SK하이닉스",
      "code": "000660",
      "logo": "SK",
      "price": 2201000.0,
      "change": -6.06,
      "prevClose": 2343000.0,
      "trend": [
        1.194,
        1.204,
        1.1631,
        0.9936,
        1.1018,
        1.0645,
        1.0
      ],
      "volume": 6013581,
      "reasons": []
    },
    {
      "group": "fixed",
      "name": "삼성전기",
      "code": "009150",
      "logo": "전기",
      "price": 1648000.0,
      "change": -9.85,
      "prevClose": 1828000.0,
      "trend": [
        1.2367,
        1.3252,
        1.338,
        1.1687,
        1.2069,
        1.1092,
        1.0
      ],
      "volume": 1106869,
      "reasons": []
    },
    {
      "group": "us_semi",
      "name": "Intel",
      "code": "INTC",
      "logo": "INTC",
      "price": 110.46,
      "change": -9.61,
      "prevClose": 122.2,
      "trend": [
        1.1617,
        1.1925,
        1.2641,
        1.1499,
        1.0895,
        1.1063,
        1.0
      ],
      "volume": 74375661,
      "reasons": []
    },
    {
      "group": "us_semi",
      "name": "NVIDIA",
      "code": "NVDA",
      "logo": "NV",
      "price": 195.95,
      "change": 0.2,
      "prevClose": 195.55,
      "trend": [
        0.9825,
        0.995,
        1.0211,
        1.0083,
        0.9943,
        0.998,
        1.0
      ],
      "volume": 55114656,
      "reasons": []
    },
    {
      "group": "us_semi",
      "name": "Micron",
      "code": "MU",
      "logo": "MU",
      "price": 926.22,
      "change": -5.94,
      "prevClose": 984.75,
      "trend": [
        1.2223,
        1.2363,
        1.246,
        1.1143,
        1.0531,
        1.0632,
        1.0
      ],
      "volume": 29672949,
      "reasons": []
    }
  ],
  "news": [
    {
      "tag": "한국",
      "text": "온통 파란 주식창 \"안 보려고 해요\"‥'반도체 비중 축소' 권고 나왔다",
      "impact": "neutral",
      "published": "Tue, 07 Jul 2026 10:51:36 GMT"
    },
    {
      "tag": "한국",
      "text": "삼성전자 최대 실적 발표 날... 코스피 8% 폭락, 매매 정지",
      "impact": "neutral",
      "published": "Tue, 07 Jul 2026 06:59:00 GMT"
    },
    {
      "tag": "한국",
      "text": "'반도체 저승사자' 또 등판…\"삼전닉스 고점 근접\" 경고",
      "impact": "neutral",
      "published": "Tue, 07 Jul 2026 13:07:00 GMT"
    },
    {
      "tag": "한국",
      "text": "코스피 8%대 폭락에 서킷브레이커 발동…'삼전닉스'도 10% 가까이 급락",
      "impact": "neutral",
      "published": "Tue, 07 Jul 2026 05:03:34 GMT"
    },
    {
      "tag": "미국",
      "text": "\"고민하는 순간 기회 놓친다\"…하이닉스, 나스닥 상장 앞두고 목표가 또 상향",
      "impact": "neutral",
      "published": "Mon, 06 Jul 2026 23:00:53 GMT"
    },
    {
      "tag": "미국",
      "text": "삼성 2분기 영업익 89.4조...엔비디아 넘어 세계 1위",
      "impact": "neutral",
      "published": "Tue, 07 Jul 2026 12:50:00 GMT"
    },
    {
      "tag": "미국",
      "text": "삼성전자 2분기 영업이익 또 ‘사상최대’…엔비디아 넘었다",
      "impact": "neutral",
      "published": "Tue, 07 Jul 2026 12:01:00 GMT"
    },
    {
      "tag": "미국",
      "text": "[미국 주식 돋보기] AI 뒤처졌던 애플의 역설 … 다시 시총 1위 넘본다",
      "impact": "neutral",
      "published": "Tue, 07 Jul 2026 08:57:54 GMT"
    },
    {
      "tag": "전쟁",
      "text": "중동 전쟁에 “트럼프 만세”...檢, ‘14조 유가 담합’ 정유 4사·임직원 기소",
      "impact": "neg",
      "published": "Mon, 06 Jul 2026 09:53:00 GMT"
    },
    {
      "tag": "전쟁",
      "text": "중동전쟁에 \"트럼프 만세\" 외친 정유사…경제위기를 폭리 기회로(종합)",
      "impact": "neg",
      "published": "Mon, 06 Jul 2026 08:02:00 GMT"
    }
  ],
  "summary": ""
}